Metadata-Version: 1.2
Name: kjson
Version: 0.1.2
Summary: A JSON encoder and decoder with support for Python types.
Home-page: https://bitbucket.org/tran-smit/py-kjson
Author: Tran-Smit Software
Author-email: frank@tran-smit.nl
License: ISC
Platform: UNKNOWN
Requires-Python: >=3.6.0
